nvtripy/__init__.py
nvtripy/__init__.pyi
nvtripy/config.py
nvtripy/constants.py
nvtripy/export.py
nvtripy/types.py
nvtripy/backend/__init__.py
nvtripy/backend/api/__init__.py
nvtripy/backend/api/bounds.py
nvtripy/backend/api/compile.py
nvtripy/backend/api/executable.py
nvtripy/backend/api/input_info.py
nvtripy/backend/api/named_dimension.py
nvtripy/backend/api/stream.py
nvtripy/backend/mlir/__init__.py
nvtripy/backend/mlir/compiler.py
nvtripy/backend/mlir/memref.py
nvtripy/backend/mlir/utils.py
nvtripy/common/__init__.py
nvtripy/common/datatype.py
nvtripy/common/device.py
nvtripy/common/exception.py
nvtripy/frontend/__init__.py
nvtripy/frontend/dimension_size.py
nvtripy/frontend/tensor.py
nvtripy/frontend/utils.py
nvtripy/frontend/module/__init__.py
nvtripy/frontend/module/batchnorm.py
nvtripy/frontend/module/embedding.py
nvtripy/frontend/module/groupnorm.py
nvtripy/frontend/module/instancenorm.py
nvtripy/frontend/module/layernorm.py
nvtripy/frontend/module/linear.py
nvtripy/frontend/module/module.py
nvtripy/frontend/module/parameter.py
nvtripy/frontend/module/sequential.py
nvtripy/frontend/module/conv/__init__.py
nvtripy/frontend/module/conv/base.py
nvtripy/frontend/module/conv/conv.py
nvtripy/frontend/module/conv/conv_transpose.py
nvtripy/frontend/module/conv/utils.py
nvtripy/frontend/ops/__init__.py
nvtripy/frontend/ops/_registry.py
nvtripy/frontend/ops/allclose.py
nvtripy/frontend/ops/arange.py
nvtripy/frontend/ops/cast.py
nvtripy/frontend/ops/concatenate.py
nvtripy/frontend/ops/copy.py
nvtripy/frontend/ops/cumsum.py
nvtripy/frontend/ops/dequantize.py
nvtripy/frontend/ops/equal.py
nvtripy/frontend/ops/expand.py
nvtripy/frontend/ops/flatten.py
nvtripy/frontend/ops/flip.py
nvtripy/frontend/ops/full.py
nvtripy/frontend/ops/gather.py
nvtripy/frontend/ops/iota.py
nvtripy/frontend/ops/masked_fill.py
nvtripy/frontend/ops/matmul.py
nvtripy/frontend/ops/ones.py
nvtripy/frontend/ops/outer.py
nvtripy/frontend/ops/pad.py
nvtripy/frontend/ops/permute.py
nvtripy-0.1.4.dist-info/LICENSE
nvtripy-0.1.4.dist-info/METADATA
nvtripy-0.1.4.dist-info/NOTICE
nvtripy-0.1.4.dist-info/WHEEL
nvtripy-0.1.4.dist-info/top_level.txt
nvtripy-0.1.4.dist-info/RECORD
