Metadata-Version: 2.1
Name: nvtripy
Version: 0.1.4
Summary: Tripy: A Python Programming Model For TensorRT
Author-email: NVIDIA <svc_tensorrt@nvidia.com>
License: Apache 2.0
Project-URL: Repository, https://github.com/NVIDIA/tensorrt-incubator/tripy/
Project-URL: Issues, https://github.com/NVIDIA/tensorrt-incubator/issues
Project-URL: Documentation, https://nvidia.github.io/TensorRT-Incubator/
Requires-Python: >=3.9
License-File: LICENSE
License-File: NOTICE
Requires-Dist: tensorrt<=10.13.0.35,>=10.11
Requires-Dist: mlir-tensorrt-compiler==0.1.43+cuda12.trt109
Requires-Dist: mlir-tensorrt-runtime==0.1.43+cuda12.trt109
Requires-Dist: colored==2.2.3
Provides-Extra: build
Requires-Dist: setuptools==75.3.0; extra == "build"
Requires-Dist: wheel==0.44.0; extra == "build"
Requires-Dist: mypy==1.11.0; extra == "build"
Provides-Extra: dev
Requires-Dist: pre-commit==3.6.0; extra == "dev"
Provides-Extra: doc_test_common
Requires-Dist: black==24.10.0; extra == "doc-test-common"
Requires-Dist: torch==2.4.0+cu121; extra == "doc-test-common"
Requires-Dist: numpy==1.25.0; extra == "doc-test-common"
Requires-Dist: nvidia-cuda-nvrtc-cu12; extra == "doc-test-common"
Requires-Dist: cupy-cuda12x; extra == "doc-test-common"
Provides-Extra: docs
Requires-Dist: sphinx==7.2.6; extra == "docs"
Requires-Dist: furo==2024.8.6; extra == "docs"
Requires-Dist: sphinx-copybutton==0.5.2; extra == "docs"
Requires-Dist: sphinx-toolbox==3.5.0; extra == "docs"
Requires-Dist: docutils==0.20.1; extra == "docs"
Requires-Dist: myst-parser==2.0.0; extra == "docs"
Requires-Dist: sphinxcontrib-mermaid==0.9.2; extra == "docs"
Requires-Dist: nvtripy[doc_test_common]; extra == "docs"
Requires-Dist: nvidia-modelopt==0.11.1; extra == "docs"
Requires-Dist: transformers==4.44.2; extra == "docs"
Requires-Dist: datasets==2.21.0; extra == "docs"
Provides-Extra: test
Requires-Dist: pytest==7.1.3; extra == "test"
Requires-Dist: pytest-virtualenv==1.8.0; extra == "test"
Requires-Dist: pytest-profiling==1.7.0; extra == "test"
Requires-Dist: pytest-cov==4.1.0; extra == "test"
Requires-Dist: pytest-xdist==3.6.1; extra == "test"
Requires-Dist: pytest-benchmark==4.0.0; extra == "test"
Requires-Dist: pytest-lazy-fixture==0.6.3; extra == "test"
Requires-Dist: pytest-mock==3.14.0; extra == "test"
Requires-Dist: path.py==12.5.0; extra == "test"
Requires-Dist: triton==3.0.0; extra == "test"
Requires-Dist: snakeviz==2.2.0; extra == "test"
Requires-Dist: coverage==7.4.1; extra == "test"
Requires-Dist: vulture==2.11; extra == "test"
Requires-Dist: nvtripy[doc_test_common]; extra == "test"
Requires-Dist: pytest-notebook==0.10.0; extra == "test"
Requires-Dist: notebook==7.2.2; extra == "test"
Requires-Dist: polygraphy==0.49.20; extra == "test"
